peachplumear/Yamaha-Grand-Lite-v2.0.sf2
peachplumear/__init__.py
peachplumear/challenge.py
peachplumear/gui.py
peachplumear/Fluidsynth/osx/fluidsynth
peachplumear/Fluidsynth/win/libfluidsynth-2.dll
peachplumear/Fluidsynth/win/libglib-2.0-0.dll
peachplumear/Fluidsynth/win/libgobject-2.0-0.dll
peachplumear/Fluidsynth/win/libgthread-2.0-0.dll
peachplumear/Fluidsynth/win/libinstpatch-2.dll
peachplumear/Fluidsynth/win/libintl-8.dll
peachplumear/Fluidsynth/win/libsndfile-1.dll
peachplumear/Images/8ave.png
peachplumear/Images/BPM.png
peachplumear/Images/BPMdownB.png
peachplumear/Images/BPMupB.png
peachplumear/Images/Chord.png
peachplumear/Images/I.png
peachplumear/Images/II.png
peachplumear/Images/III.png
peachplumear/Images/IV.png
peachplumear/Images/Icon.png
peachplumear/Images/KeyLock.png
peachplumear/Images/New.png
peachplumear/Images/PlayB.png
peachplumear/Images/PlayChB.png
peachplumear/Images/RevealB.png
peachplumear/Images/Scale.png
peachplumear/Images/V.png
peachplumear/Images/VI.png
peachplumear/Images/VII.png
peachplumear/Images/icon.ico
peachplumear/Images/inv.png
peachplumear/Images/maj.png
peachplumear/Images/min.png
peachplumear/Images/nInt.png
peachplumear/Images/playInt.png
peachplumear/mingus/__init__.py
peachplumear/mingus/containers/__init__.py
peachplumear/mingus/containers/bar.py
peachplumear/mingus/containers/composition.py
peachplumear/mingus/containers/instrument.py
peachplumear/mingus/containers/mt_exceptions.py
peachplumear/mingus/containers/note.py
peachplumear/mingus/containers/note_container.py
peachplumear/mingus/containers/suite.py
peachplumear/mingus/containers/track.py
peachplumear/mingus/core/__init__.py
peachplumear/mingus/core/chords.py
peachplumear/mingus/core/intervals.py
peachplumear/mingus/core/keys.py
peachplumear/mingus/core/meter.py
peachplumear/mingus/core/mt_exceptions.py
peachplumear/mingus/core/notes.py
peachplumear/mingus/core/progressions.py
peachplumear/mingus/core/scales.py
peachplumear/mingus/core/value.py
peachplumear-0.0.26.dist-info/LICENCE.txt
peachplumear-0.0.26.dist-info/METADATA
peachplumear-0.0.26.dist-info/WHEEL
peachplumear-0.0.26.dist-info/top_level.txt
peachplumear-0.0.26.dist-info/RECORD
