Metadata-Version: 2.1
Name: peachplumear
Version: 0.0.26
Summary: Testing and training your musical ear, moveable do-oriented.
Home-page: https://github.com/TomPJWyatt/PeachPlumEar
Author: Tom Wyatt
Author-email: womtyatt@gmail.com
License: UNKNOWN
Platform: UNKNOWN
Classifier: Programming Language :: Python :: 3
Classifier: License :: OSI Approved :: MIT License
Classifier: Operating System :: OS Independent
Requires-Dist: six
Requires-Dist: numpy
